tesserai/__init__.py
tesserai/api.py
tesserai/cli/__init__.py
tesserai/cli/auth.py
tesserai/cli/cluster.py
tesserai/cli/model.py
tesserai/cli/saga.py
tesserai/cli/tensorboard.py
tesserai/rproxy/__init__.py
tesserai/rproxy/rproxy
tesserai-0.2.1.dist-info/LICENSE.txt
tesserai-0.2.1.dist-info/METADATA
tesserai-0.2.1.dist-info/RECORD
tesserai-0.2.1.dist-info/WHEEL
tesserai-0.2.1.dist-info/entry_points.txt
tesserai-0.2.1.dist-info/top_level.txt
