Metadata-Version: 2.1
Name: tesserai
Version: 0.2.1
Summary: Accelerate TensorFlow with cloud GPUs in one line of code
Home-page: https://github.com/tesserai/tesserai
Author: Adam Bouhenguel
Author-email: adam@tesserai.com
Maintainer: Adam Bouhenguel
Maintainer-email: adam@tesserai.com
License: UNKNOWN
Keywords: gpu,tensorflow,ai,machine learning,ml
Platform: UNKNOWN
Classifier: Development Status :: 3 - Alpha
Classifier: Intended Audience :: Developers
Classifier: Natural Language :: English
Classifier: Operating System :: OS Independent
Classifier: Programming Language :: Python
Classifier: Programming Language :: Python :: 3
Classifier: Programming Language :: Python :: Implementation :: CPython
Classifier: Topic :: Software Development :: Libraries :: Python Modules
Requires-Dist: bravado
Requires-Dist: click
Requires-Dist: humanize
Requires-Dist: pyyaml
Requires-Dist: texttable
Requires-Dist: tqdm
Requires-Dist: requests
Requires-Dist: requests-toolbelt
